{
  "AMARANTE": {
    "last_update": "2026-04-29T14:06:08.377350",
    "source": "IPMA",
    "station_id": 1210657,
    "station_name": "Luzim",
    "station_dist_km": 19.8,
    "ipma_temp": 14.9,
    "ipma_wind": -99.0,
    "ipma_hum": 90.0,
    "om_temp": 14.6,
    "om_wind": 12.5,
    "temp_offset": 0.3,
    "wind_factor": 0.5
  },
  "S. DA ABOBOREIRA": {
    "last_update": "2026-04-29T14:06:08.377350",
    "source": "IPMA",
    "station_id": 1210657,
    "station_name": "Luzim",
    "station_dist_km": 17.0,
    "ipma_temp": 14.9,
    "ipma_wind": -99.0,
    "ipma_hum": 90.0,
    "om_temp": 14.6,
    "om_wind": 12.5,
    "temp_offset": 0.3,
    "wind_factor": 0.5
  },
  "SERRA DO MARÃO": {
    "last_update": "2026-04-29T14:06:08.377350",
    "source": "IPMA",
    "station_id": 1240566,
    "station_name": "Vila Real (Cidade)",
    "station_dist_km": 13.9,
    "ipma_temp": 14.6,
    "ipma_wind": 2.5,
    "ipma_hum": 94.0,
    "om_temp": 16.0,
    "om_wind": 5.1,
    "temp_offset": -1.4,
    "wind_factor": 0.5
  },
  "GAVIÃO": {
    "last_update": "2026-04-29T14:06:08.377350",
    "source": "IPMA",
    "station_id": 1240566,
    "station_name": "Vila Real (Cidade)",
    "station_dist_km": 17.5,
    "ipma_temp": 14.6,
    "ipma_wind": 2.5,
    "ipma_hum": 94.0,
    "om_temp": 16.0,
    "om_wind": 5.1,
    "temp_offset": -1.4,
    "wind_factor": 0.5
  },
  "SERRA DO ALVÃO": {
    "last_update": "2026-04-29T14:06:08.377350",
    "source": "IPMA",
    "station_id": 1240566,
    "station_name": "Vila Real (Cidade)",
    "station_dist_km": 9.0,
    "ipma_temp": 14.6,
    "ipma_wind": 2.5,
    "ipma_hum": 94.0,
    "om_temp": 16.0,
    "om_wind": 5.1,
    "temp_offset": -1.4,
    "wind_factor": 0.5
  },
  "SRA. GRAÇA": {
    "last_update": "2026-04-29T14:06:08.377350",
    "source": "IPMA",
    "station_id": 1210630,
    "station_name": "Cabeceiras de Basto",
    "station_dist_km": 13.8,
    "ipma_temp": 15.6,
    "ipma_wind": 6.5,
    "ipma_hum": 97.0,
    "om_temp": 15.2,
    "om_wind": 8.4,
    "temp_offset": 0.4,
    "wind_factor": 0.774
  }
}